{
    "playerInfo": {
        "nickname": "孤傲-魈少",
        "level": 59,
        "signature": "为什么那么多人喷伞兵,伞兵厨心痛",
        "worldLevel": 8,
        "nameCardId": 210058,
        "finishAchievementNum": 436,
        "towerFloorIndex": 12,
        "towerLevelIndex": 1,
        "showAvatarInfoList": [
            {
                "avatarId": 10000026,
                "level": 90
            },
            {
                "avatarId": 10000022,
                "level": 90
            },
            {
                "avatarId": 10000030,
                "level": 90
            },
            {
                "avatarId": 10000052,
                "level": 90
            },
            {
                "avatarId": 10000029,
                "level": 90
            },
            {
                "avatarId": 10000016,
                "level": 90,
                "costumeId": 201601
            },
            {
                "avatarId": 10000037,
                "level": 90
            },
            {
                "avatarId": 10000033,
                "level": 90
            }
        ],
        "showNameCardIdList": [
            210004,
            210005,
            210073,
            210092,
            210044,
            210046,
            210053,
            210112,
            210007
        ],
        "profilePicture": {
            "avatarId": 10000026
        }
    },
    "ttl": 180
}